{
    "TITLE": "全解析可見光衛星雲圖-全景 ",
    "NODE": "25877",
    "DESC": "保持全解析度的可見光衛星雲圖-可見光",
    "SCHEMA": "可見光衛星雲圖之解析度為22000x22000",
    "AGENCY": "交通部中央氣象局",
    "AGENCY_CONTACT": "王 女士 (02-23491310)",
    "UPDATE_FREQ": "即時",
    "LICENCE": "政府資料開放授權條款-第1版",
    "CHARGE": "免費",
    "DATE_PUBLISH": "2015/12/30",
    "DATA_TYPE": "系統介接程式",
    "DATE_UPDATE_META": "2015/12/30 16:00",
    "KEYWORDS": [],
    "CATEGORY": "其他",
    "SERVICE_TYPE": "生活安全及品質",
    "NOTES": "授權說明網址: http://data.gov.tw/license",
    "Stats": "瀏覽次數: 885 下載次數: 81 意見數: 0 ",
    "VIEWS": "885",
    "DOWNLOAD": "81",
    "COMMENTS": "0",
    "RESOURCE": [
        {
            "SCHEMA": "可見光衛星雲圖之解析度為22000x22000",
            "RES_FILETYPE": "XML",
            "RES_ENCODE": "UTF-8",
            "REC_COUNT": "0",
            "RES_URL": "http://opendata.cwb.gov.tw/govdownload?dataid=O-B0033-002&authorizationkey=rdec-key-123-45678-011121314",
            "RES_DESC": "保持全解析度的可見光衛星雲圖-可見光，解析度為22000x22000",
            "RES_DATE_UPDATE_META": "2018/03/09 12:14"
        }
    ]
}