{
    "TITLE": "月出月沒時刻",
    "NODE": "75381",
    "DESC": "全臺各縣市每天的月出、月沒及月球過中天等時刻資料，並含有月出月沒時之方位及過中天時之仰角資料",
    "SCHEMA": [
        "縣市名稱",
        "日期",
        "月出時刻",
        "月出方位角",
        "月球過中天時刻",
        "月球過中天仰角",
        "月沒時刻",
        "月沒方位角"
    ],
    "AGENCY": "交通部中央氣象局",
    "AGENCY_CONTACT": "鄭 先生 (02-23491097)",
    "UPDATE_FREQ": "每年",
    "LICENCE": "政府資料開放授權條款-第1版",
    "CHARGE": "免費",
    "DATE_PUBLISH": "2018/01/26",
    "DATA_TYPE": "系統介接程式",
    "DATE_UPDATE_META": "2018/01/26 11:42",
    "KEYWORDS": [],
    "CATEGORY": "其他",
    "SERVICE_TYPE": "生活安全及品質",
    "Stats": "瀏覽次數: 40 下載次數: 7 意見數: 0 ",
    "VIEWS": "40",
    "DOWNLOAD": "7",
    "COMMENTS": "0",
    "RESOURCE": [
        {
            "SCHEMA": "縣市名稱、日期、月出時刻、月出方位角、月球過中天時刻、月球過中天仰角、月沒時刻、月沒方位角",
            "RES_FILETYPE": "XML",
            "RES_ENCODE": "UTF-8",
            "REC_COUNT": "0",
            "RES_URL": "http://opendata.cwb.gov.tw/govdownload?dataid=A-B0063-001&authorizationkey=rdec-key-123-45678-011121314",
            "RES_DESC": "全臺各縣市年度逐日月出月沒時刻資料",
            "RES_DATE_UPDATE_META": "2018/02/12 15:13"
        }
    ]
}