{
    "TITLE": "鄉鎮天氣預報-台灣未來1週天氣預報",
    "NODE": "9308",
    "DESC": "臺灣各鄉鎮市區預報資料",
    "SCHEMA": [
        "臺灣各鄉鎮市區未來2天(逐3小時)",
        "及未來1週天氣預報"
    ],
    "AGENCY": "交通部中央氣象局",
    "AGENCY_CONTACT": "賴冠良 先生 (02-23491217)",
    "UPDATE_FREQ": "不更新",
    "LICENCE": "政府資料開放授權條款-第1版",
    "CHARGE": "免費",
    "DATE_PUBLISH": "2015/12/29",
    "DATA_TYPE": "系統介接程式",
    "DATE_UPDATE_META": "2014/09/30 14:55",
    "KEYWORDS": [],
    "CATEGORY": "其他",
    "SERVICE_TYPE": "生活安全及品質",
    "NOTES": "更新頻率說明: 每6小時授權說明網址: http://data.gov.tw/license",
    "Stats": "瀏覽次數: 1760 下載次數: 813 意見數: 1 ",
    "VIEWS": "1760",
    "DOWNLOAD": "813",
    "COMMENTS": "1",
    "RESOURCE": [
        {
            "SCHEMA": "臺灣各鄉鎮市區未來2天(逐3小時)、及未來1週天氣預報",
            "RES_FILETYPE": "XML",
            "RES_ENCODE": "UTF-8",
            "REC_COUNT": "0",
            "RES_URL": "http://opendata.cwb.gov.tw/govdownload?dataid=F-D0047-091&authorizationkey=rdec-key-123-45678-011121314",
            "RES_DESC": " ",
            "RES_DATE_UPDATE_META": "2018/03/09 12:12"
        },
        {
            "SCHEMA": "臺灣各鄉鎮市區未來2天(逐3小時)、及未來1週天氣預報",
            "RES_FILETYPE": "PDF",
            "RES_ENCODE": "UTF-8",
            "REC_COUNT": "0",
            "RES_URL": "http://opendata.cwb.gov.tw/opendatadoc/MFC/ForecastElement.pdf",
            "RES_DESC": " ",
            "RES_DATE_UPDATE_META": "2017/11/20 21:35"
        },
        {
            "SCHEMA": "臺灣各鄉鎮市區未來2天(逐3小時)、及未來1週天氣預報",
            "RES_FILETYPE": "PDF",
            "RES_ENCODE": "UTF-8",
            "REC_COUNT": "0",
            "RES_URL": "http://opendata.cwb.gov.tw/opendatadoc/CWB_Opendata_API_V1.2.pdf",
            "RES_DESC": "API使用說明",
            "RES_DATE_UPDATE_META": "2017/10/26 16:12"
        },
        {
            "SCHEMA": "臺灣各鄉鎮市區未來2天(逐3小時)、及未來1週天氣預報",
            "RES_FILETYPE": "API",
            "RES_ENCODE": "UTF-8",
            "REC_COUNT": "0",
            "RES_URL": "https://opendata.cwb.gov.tw/api/v1/rest/datastore/F-D0047-0091?Authorization=rdec-key-123-45678-011121314",
            "RES_DESC": "API",
            "RES_DATE_UPDATE_META": "2017/10/06 10:16"
        },
        {
            "SCHEMA": "臺灣各鄉鎮市區未來2天(逐3小時)、及未來1週天氣預報",
            "RES_FILETYPE": "PDF",
            "RES_ENCODE": "UTF-8",
            "REC_COUNT": "0",
            "RES_URL": "http://opendata.cwb.gov.tw/opendatadoc/MFC/D0047.pdf",
            "RES_DESC": "天氣描述代碼",
            "RES_DATE_UPDATE_META": "2017/11/20 21:35"
        }
    ]
}